arcanumpy/SeabornFig2Grid.py
arcanumpy/__init__.py
arcanumpy/__version__.py
arcanumpy/arcanumpy.py
arcanumpy/get_files_from_web.py
arcanumpy/histogram_plots.py
arcanumpy/histogram_sample.py
arcanumpy/img_to_mp4.py
arcanumpy/seaborn_plots.py
arcanumpy/seaborn_plots_fncs.py
arcanumpy/text_color_fnc.py
arcanumpy/tests/__init__.py
arcanumpy/tests/test_arcanumpy.py
arcanumpy-0.1.1.dist-info/LICENSE
arcanumpy-0.1.1.dist-info/METADATA
arcanumpy-0.1.1.dist-info/WHEEL
arcanumpy-0.1.1.dist-info/top_level.txt
arcanumpy-0.1.1.dist-info/RECORD
