Metadata-Version: 2.1
Name: arcanumpy
Version: 0.1.1
Summary: Personal collection of various Python tools and utilities.
Home-page: https://qudsiramiz.space/arcanumpy
Author: Qudsi, Ramiz
Author-email: qudsiramiz@gmail.com
License: GNU GPLv3
Keywords: packages
Requires-Python: >=3.10
License-File: LICENSE
Requires-Dist: pandas
Requires-Dist: scikit-learn
Requires-Dist: seaborn
Requires-Dist: cdflib
Requires-Dist: imageio
